odoo/addons/pos_config_logo/README.rst
odoo/addons/pos_config_logo/__init__.py
odoo/addons/pos_config_logo/__manifest__.py
odoo/addons/pos_config_logo/i18n/it.po
odoo/addons/pos_config_logo/i18n/pos_config_logo.pot
odoo/addons/pos_config_logo/models/__init__.py
odoo/addons/pos_config_logo/models/pos_config.py
odoo/addons/pos_config_logo/readme/CONFIGURE.md
odoo/addons/pos_config_logo/readme/CONTEXT.md
odoo/addons/pos_config_logo/readme/CONTRIBUTORS.md
odoo/addons/pos_config_logo/readme/DESCRIPTION.md
odoo/addons/pos_config_logo/readme/USAGE.md
odoo/addons/pos_config_logo/static/description/icon.png
odoo/addons/pos_config_logo/static/description/index.html
odoo/addons/pos_config_logo/static/src/js/models.js
odoo/addons/pos_config_logo/views/assets.xml
odoo/addons/pos_config_logo/views/pos_config_views.xml
odoo14_addon_pos_config_logo-14.0.1.0.1.dev5.dist-info/METADATA
odoo14_addon_pos_config_logo-14.0.1.0.1.dev5.dist-info/WHEEL
odoo14_addon_pos_config_logo-14.0.1.0.1.dev5.dist-info/top_level.txt
odoo14_addon_pos_config_logo-14.0.1.0.1.dev5.dist-info/RECORD
